mprerun/__init__.py
mprerun/__main__.py
mprerun/config.py
mprerun/dtw/__init__.py
mprerun/dtw/mediapipe_dtw.py
mprerun/pose/__init__.py
mprerun/pose/mediapipe_pose.py
mprerun/pose/mediapipe_pose_config.py
mprerun/pose/mediapipe_pose_video.py
mprerun/pose/mediapipe_pose_video_base.py
mprerun/pose/mediapipe_pose_video_data.py
mprerun/pose/mediapipe_pose_video_viewer.py
mprerun-0.1.2.dist-info/METADATA
mprerun-0.1.2.dist-info/WHEEL
mprerun-0.1.2.dist-info/entry_points.txt
mprerun-0.1.2.dist-info/RECORD
