Metadata-Version: 2.3
Name: mprerun
Version: 0.1.2
Summary: MediaPipe + Rerun..
Author-email: zhwuzhiguo <zhwuzhiguo@gmail.com>
Requires-Python: >=3.8
Requires-Dist: fastdtw>=0.3.4
Requires-Dist: loguru>=0.7.2
Requires-Dist: mediapipe>=0.10.18
Requires-Dist: pydantic>=2.9.2
Requires-Dist: rerun-sdk>=0.19.0
